canvasacademicanalyzer-0.1.0.dist-info/licenses/LICENSE.txt
canvasacademicinsights/__init__.py
canvasacademicinsights/canvasaianalyzer/__init__.py
canvasacademicinsights/canvasaianalyzer/clean.py
canvasacademicinsights/canvasaianalyzer/grades.py
canvasacademicinsights/canvasaianalyzer/model.py
canvasacademicinsights/canvasaianalyzer/organize.py
canvasacademicinsights/canvasmain/__init__.py
canvasacademicinsights/canvasmain/canvasdataretriever.py
canvasacademicinsights/canvasmain/canvasinsights.py
canvasacademicinsights/canvasvisualizer/__init__.py
canvasacademicinsights/canvasvisualizer/canvassummaryvisualization.py
canvasacademicinsights/canvasvisualizer/canvastimevisualization.py
canvasacademicanalyzer-0.1.0.dist-info/METADATA
canvasacademicanalyzer-0.1.0.dist-info/WHEEL
canvasacademicanalyzer-0.1.0.dist-info/top_level.txt
canvasacademicanalyzer-0.1.0.dist-info/RECORD
