Metadata-Version: 2.4
Name: canvasAcademicAnalyzer
Version: 0.1.0
Summary: An example package
Author: Yue Wang, Richard Hua, Jordan Kaseram
Project-URL: Homepage, https://github.com/yueywangse/533Step3
Project-URL: Issues, https://github.com/yueywangse/533Step3/issues
Classifier: Programming Language :: Python :: 3
Classifier: License :: OSI Approved :: MIT License
Classifier: Operating System :: OS Independent
Requires-Python: >=3.8
License-File: LICENSE.txt
Dynamic: license-file
